crispy_forms_semantic_ui/README.rst
crispy_forms_semantic_ui/__init__.py
crispy_forms_semantic_ui/__init__.pyc
crispy_forms_semantic_ui/apps.py
crispy_forms_semantic_ui/templates/semantic-ui/betterform.html
crispy_forms_semantic_ui/templates/semantic-ui/display_form.html
crispy_forms_semantic_ui/templates/semantic-ui/errors.html
crispy_forms_semantic_ui/templates/semantic-ui/errors_formset.html
crispy_forms_semantic_ui/templates/semantic-ui/field.html
crispy_forms_semantic_ui/templates/semantic-ui/field.strict.html
crispy_forms_semantic_ui/templates/semantic-ui/multifield.html
crispy_forms_semantic_ui/templates/semantic-ui/uni_form.html
crispy_forms_semantic_ui/templates/semantic-ui/uni_formset.html
crispy_forms_semantic_ui/templates/semantic-ui/whole_uni_form.html
crispy_forms_semantic_ui/templates/semantic-ui/whole_uni_formset.html
crispy_forms_semantic_ui/templates/semantic-ui/layout/baseinput.html
crispy_forms_semantic_ui/templates/semantic-ui/layout/buttonholder.html
crispy_forms_semantic_ui/templates/semantic-ui/layout/div.html
crispy_forms_semantic_ui/templates/semantic-ui/layout/fieldset.html
crispy_forms_semantic_ui/templates/semantic-ui/layout/multifield.html
crispy_forms_semantic_ui-0.2.0.dist-info/DESCRIPTION.rst
crispy_forms_semantic_ui-0.2.0.dist-info/LICENSE.txt
crispy_forms_semantic_ui-0.2.0.dist-info/METADATA
crispy_forms_semantic_ui-0.2.0.dist-info/RECORD
crispy_forms_semantic_ui-0.2.0.dist-info/WHEEL
crispy_forms_semantic_ui-0.2.0.dist-info/metadata.json
crispy_forms_semantic_ui-0.2.0.dist-info/top_level.txt
