Metadata-Version: 1.1
Name: crispy-forms-semantic-ui
Version: 0.2.0
Summary: Semantic UI templates for django-crispy-forms.
Home-page: https://github.com/acidjunk/crispy-forms-semanticUI-templates
Author: Rene Dohmen
Author-email: acidjunk@gmail.com
License: GPLv3 License
Keywords: django crispy-forms semantic-ui forms
Platform: UNKNOWN
Classifier: Environment :: Web Environment
Classifier: Framework :: Django
Classifier: Intended Audience :: Developers
Classifier: License :: OSI Approved :: BSD License
Classifier: Operating System :: OS Independent
Classifier: Programming Language :: Python
Classifier: Programming Language :: Python :: 2.7
Classifier: Programming Language :: Python :: 3
Classifier: Programming Language :: Python :: 3.2
Classifier: Programming Language :: Python :: 3.3
Classifier: Programming Language :: Python :: 3.4
Classifier: Programming Language :: Python :: 3.5
Classifier: Programming Language :: Python :: 3.6
Classifier: Topic :: Internet :: WWW/HTTP
Classifier: Topic :: Internet :: WWW/HTTP :: Dynamic Content
